{
  "banners": [
    {
      "id": 1,
      "enabled": true,
      "mainImage": "./image/p-p-1.jpg",
      "logoImage": "./image/p-p-1logo.png",
      "title": "XRE BOOKING",
      "description": "Your trusted partner for live music events across Asia.",
      "buttonText": "Learn More",
      "link": "https://xrebooking.com"
    },
    {
      "id": 2,
      "enabled": true,
      "mainImage": "./image/p-p-2.jpg",
      "logoImage": "./image/p-p-2logo.png",
      "title": "Kids Union Records",
      "description": "Independent record label supporting emerging artists.",
      "buttonText": "Visit Website",
      "link": "https://kids-union.com"
    },
    {
      "id": 3,
      "enabled": true,
      "mainImage": "./image/p-p-3.png",
      "logoImage": "./image/p-p-3logo.png",
      "title": "Music Festival Asia",
      "description": "Connecting music lovers across the continent.",
      "buttonText": "Explore",
      "link": "https://musicfestivalasia.com"
    },
    {
      "id": 4,
      "enabled": true,
      "mainImage": "./image/p-p-4.jpg",
      "logoImage": "./image/p-p-4logo.png",
      "title": "Live Nation",
      "description": "Global leader in live entertainment.",
      "buttonText": "Partner With Us",
      "link": "https://livenation.com"
    },
    {
      "id": 5,
      "enabled": false,
      "mainImage": "",
      "logoImage": "",
      "title": "",
      "description": "",
      "buttonText": "",
      "link": ""
    },
    {
      "id": 6,
      "enabled": false,
      "mainImage": "",
      "logoImage": "",
      "title": "",
      "description": "",
      "buttonText": "",
      "link": ""
    },
    {
      "id": 7,
      "enabled": false,
      "mainImage": "",
      "logoImage": "",
      "title": "",
      "description": "",
      "buttonText": "",
      "link": ""
    },
    {
      "id": 8,
      "enabled": false,
      "mainImage": "",
      "logoImage": "",
      "title": "",
      "description": "",
      "buttonText": "",
      "link": ""
    },
    {
      "id": 9,
      "enabled": false,
      "mainImage": "",
      "logoImage": "",
      "title": "",
      "description": "",
      "buttonText": "",
      "link": ""
    }
  ]
}