{
  "banners": [
    {
      "title": "LIVEGIGS CN",
      "details": "Head to our homepage at livegigs.cn and follow us there for exclusive content, early bird tickets, and behind-the-scenes access to China's top live events!",
      "buttonText": "Go to live gigs cn",
      "link": "https://livegigs.cn",
      "backgroundImage": "./image/p-p-1.jpg",
      "logo": "./image/livegigscn1.png"
    },
    {
      "title": "小子聯盟唱片",
      "details": "",
      "buttonText": "访问网站",
      "link": "https://kids-union.com",
      "backgroundImage": "./image/p-p-2.jpg",
      "logo": ""
    },
    {
      "title": "XRE BOOKING",
      "details": "Booking Agency in Punkrock, Garage, Mod, Powerpop, Surf, Poppunk, RocknRoll, Hardcore, Metal.",
      "buttonText": "XRE BOOKING",
      "link": "https://xrebooking.com",
      "backgroundImage": "./image/p-p-3.jpg",
      "logo": "./image/webtop.png"
    },
    {
      "title": "CHINESEROCKS",
      "details": "",
      "buttonText": "访问官网",
      "link": "https://chineserocks.n",
      "backgroundImage": "./image/p-p-4.jpg",
      "logo": "./image/p-p-4logo.png"
    }
  ]
}